Metadata-Version: 2.1
Name: sim_openc2
Version: 1.1.0
Summary: Produce and consume OpenC2 JSON messages
Home-page: https://github.com/oasis-open/openc2-lycan-python
Author: OASIS Open Command and Control (OpenC2) Technical Committee (TC)
License: MIT
Keywords: openc2 cyber
License-File: LICENSE
Provides-Extra: stix
Requires-Dist: stix2; extra == "stix"
